CHANGES.txt
MANIFEST.in
README.txt
setup.cfg
setup.py
docs/contributors.txt
docs/demo.txt
docs/description.txt
docs/download.txt
docs/index.txt
docs/jquery-plugin.txt
docs/news.txt
docs/paste-factories.txt
docs/storage.txt
docs/upload.txt
gp/__init__.py
gp.fileupload.egg-info/PKG-INFO
gp.fileupload.egg-info/SOURCES.txt
gp.fileupload.egg-info/dependency_links.txt
gp.fileupload.egg-info/entry_points.txt
gp.fileupload.egg-info/namespace_packages.txt
gp.fileupload.egg-info/not-zip-safe
gp.fileupload.egg-info/requires.txt
gp.fileupload.egg-info/top_level.txt
gp/fileupload/__init__.py
gp/fileupload/config.py
gp/fileupload/demo.py
gp/fileupload/resource.py
gp/fileupload/sampleapp.py
gp/fileupload/storage.py
gp/fileupload/tests.py
gp/fileupload/upload.py
gp/fileupload/static/fileupload.css
gp/fileupload/static/jquery.fileupload.auto.js
gp/fileupload/static/jquery.fileupload.js
gp/fileupload/static/jquery.js