Metadata-Version: 1.0
Name: gp.fileupload
Version: 1.2
Summary: A WSGI middleware to get some stats on large files upload,and provide a progress bar for your users
Home-page: http://www.gawel.org/docs/gp.fileupload/
Author: Gael Pasgrimaud
Author-email: gael@gawel.org
License: MIT
Keywords: wsgi middleware upload progress bar
Platform: UNKNOWN
Classifier: Programming Language :: Python
Classifier: Intended Audience :: Developers
Classifier: License :: OSI Approved :: MIT License
Classifier: Topic :: Internet :: WWW/HTTP :: WSGI :: Middleware
Classifier: Topic :: Software Development :: Libraries :: Python Modules
Classifier: Environment :: Web Environment
Classifier: Programming Language :: Python
Classifier: Programming Language :: JavaScript
